setup.py
django_emojione/__init__.py
django_emojione/functions.py
django_emojione.egg-info/PKG-INFO
django_emojione.egg-info/SOURCES.txt
django_emojione.egg-info/dependency_links.txt
django_emojione.egg-info/requires.txt
django_emojione.egg-info/top_level.txt
django_emojione/templatetags/__init__.py
django_emojione/templatetags/emojione.py