Metadata-Version: 1.1
Name: django-emojione
Version: 0.1.7.4
Summary: Wrapper for emojione to use in django.
Home-page: https://github.com/phuong/django-emojione
Author: Phuong
Author-email: boingonline@gmail.com
License: BSD License
Download-URL: https://github.com/phuong/django-emojione/archive/master.zip
Platform: UNKNOWN
Classifier: Framework :: Django
Classifier: Intended Audience :: Developers
Classifier: License :: OSI Approved :: BSD License
Classifier: Operating System :: OS Independent
Classifier: Programming Language :: Python
Classifier: Programming Language :: Python :: 2.7
Classifier: Programming Language :: Python :: 3
Classifier: Framework :: Django
Classifier: Topic :: Internet :: WWW/HTTP
Classifier: Topic :: Internet :: WWW/HTTP :: Dynamic Content
